pythonPrintAnimals/__init__.py
pythonPrintAnimals/printAnimals.py
pythonPrintAnimals/tools.py
pythonPrintAnimals-1.0.2.dist-info/LICENSE
pythonPrintAnimals-1.0.2.dist-info/METADATA
pythonPrintAnimals-1.0.2.dist-info/WHEEL
pythonPrintAnimals-1.0.2.dist-info/top_level.txt
pythonPrintAnimals-1.0.2.dist-info/RECORD
