Metadata-Version: 2.1
Name: pythonPrintAnimals
Version: 1.0.2
Summary: A simple python library that prints animals
Home-page: UNKNOWN
Author: Uarlley Amorim
License: UNKNOWN
Platform: UNKNOWN
License-File: LICENSE
Requires-Dist: plotly
